{
  "language": "ru",
  "title": "Магия словообразования 2",
  "speakers": {
    "1": "Спикер 1"
  },
  "sentences": [
    {
      "key": "000",
      "speaker": "1",
      "text": "Она видела свою подругу на рейсе в Париж.",
      "audio": "000_ru_avto.mp3",
      "audio_avto": "000_ru_avto.mp3",
      "audio_user": "",
      "audio_mic": "",
      "start": 0,
      "end": 0,
      "chain": false
    },
    {
      "key": "001",
      "speaker": "1",
      "text": "Птицы летают быстрее, чем мой Wi-Fi.",
      "audio": "001_ru_avto.mp3",
      "audio_avto": "001_ru_avto.mp3",
      "audio_user": "",
      "audio_mic": "",
      "start": 0,
      "end": 0,
      "chain": false
    },
    {
      "key": "002",
      "speaker": "1",
      "text": "Я думаю, что плач — признак слабости.",
      "audio": "002_ru_avto.mp3",
      "audio_avto": "002_ru_avto.mp3",
      "audio_user": "",
      "audio_mic": "",
      "start": 0,
      "end": 0,
      "chain": false
    },
    {
      "key": "003",
      "speaker": "1",
      "text": "Есть сильные люди, а есть слабые.",
      "audio": "003_ru_avto.mp3",
      "audio_avto": "003_ru_avto.mp3",
      "audio_user": "",
      "audio_mic": "",
      "start": 0,
      "end": 0,
      "chain": false
    },
    {
      "key": "004",
      "speaker": "1",
      "text": "Мы говорили о бедности в некоторых странах.",
      "audio": "004_ru_avto.mp3",
      "audio_avto": "004_ru_avto.mp3",
      "audio_user": "",
      "audio_mic": "",
      "start": 0,
      "end": 0,
      "chain": false
    },
    {
      "key": "005",
      "speaker": "1",
      "text": "Я слишком беден, чтобы купить второй пончик.",
      "audio": "005_ru_avto.mp3",
      "audio_avto": "005_ru_avto.mp3",
      "audio_user": "",
      "audio_mic": "",
      "start": 0,
      "end": 0,
      "chain": false
    },
    {
      "key": "006",
      "speaker": "1",
      "text": "Студенты обсудили проблему дискриминации.",
      "audio": "006_ru_avto.mp3",
      "audio_avto": "006_ru_avto.mp3",
      "audio_user": "",
      "audio_mic": "",
      "start": 0,
      "end": 0,
      "chain": false
    },
    {
      "key": "007",
      "speaker": "1",
      "text": "Мы не должны дискриминировать никого в школе.",
      "audio": "007_ru_avto.mp3",
      "audio_avto": "007_ru_avto.mp3",
      "audio_user": "",
      "audio_mic": "",
      "start": 0,
      "end": 0,
      "chain": false
    },
    {
      "key": "008",
      "speaker": "1",
      "text": "Мы прочитали об изобретении нового устройства.",
      "audio": "008_ru_avto.mp3",
      "audio_avto": "008_ru_avto.mp3",
      "audio_user": "",
      "audio_mic": "",
      "start": 0,
      "end": 0,
      "chain": false
    },
    {
      "key": "009",
      "speaker": "1",
      "text": "Я хочу изобрести подушку, которая никогда не падает.",
      "audio": "009_ru_avto.mp3",
      "audio_avto": "009_ru_avto.mp3",
      "audio_user": "",
      "audio_mic": "",
      "start": 0,
      "end": 0,
      "chain": false
    },
    {
      "key": "010",
      "speaker": "1",
      "text": "Какое последнее достижение в физике?",
      "audio": "010_ru_avto.mp3",
      "audio_avto": "010_ru_avto.mp3",
      "audio_user": "",
      "audio_mic": "",
      "start": 0,
      "end": 0,
      "chain": false
    }
  ],
  "audio_user_shared": "",
  "audio_user_shared_start": 0,
  "audio_user_shared_end": 0
}